weatherbotskeleton/ZIP_CODES.txt
weatherbotskeleton/__init__.py
weatherbotskeleton/weatherbot_skeleton.py
weatherbotskeleton-1.6.1.dist-info/LICENSE
weatherbotskeleton-1.6.1.dist-info/METADATA
weatherbotskeleton-1.6.1.dist-info/WHEEL
weatherbotskeleton-1.6.1.dist-info/top_level.txt
weatherbotskeleton-1.6.1.dist-info/RECORD
